lsp_sim/__init__.py
lsp_sim/lsp_f0_sim.py
lsp_sim/wv_lsp.py
lsp_sim-0.1.1.dist-info/licenses/LICENSE
lsp_sim-0.1.1.dist-info/METADATA
lsp_sim-0.1.1.dist-info/WHEEL
lsp_sim-0.1.1.dist-info/top_level.txt
lsp_sim-0.1.1.dist-info/RECORD
