Metadata-Version: 2.4
Name: lsp-sim
Version: 0.1.1
Summary: Locally stationary process simulation
Requires-Python: >=3.11
License-File: LICENSE
Requires-Dist: numpy>=2.3.3
Requires-Dist: scipy>=1.16.2
Provides-Extra: dev
Requires-Dist: jupyter>=1.1.1; extra == "dev"
Requires-Dist: matplotlib>=3.10.6; extra == "dev"
Requires-Dist: pytest; extra == "dev"
Dynamic: license-file
